py_lazy_vin/__init__.py
py_lazy_vin/alpha_to_numerical.py
py_lazy_vin/cd_val_to_vin_char.py
py_lazy_vin/cli.py
py_lazy_vin/hard_coded_vins.py
py_lazy_vin/helpers.py
py_lazy_vin/py_lazy_vin.py
py_lazy_vin/vin_character_weights.py
py_lazy_vin-0.0.2.dist-info/AUTHORS.rst
py_lazy_vin-0.0.2.dist-info/LICENSE
py_lazy_vin-0.0.2.dist-info/METADATA
py_lazy_vin-0.0.2.dist-info/WHEEL
py_lazy_vin-0.0.2.dist-info/entry_points.txt
py_lazy_vin-0.0.2.dist-info/top_level.txt
py_lazy_vin-0.0.2.dist-info/RECORD
