Metadata-Version: 2.1
Name: py-lazy-vin
Version: 0.0.2
Summary: A quick and dirty python library for lazily handling random VINs.
Home-page: https://github.com/tabuckner/py_lazy_vin
Author: Taylor Buckner
Author-email: tbuckner@theappraisallane.com
License: MIT license
Keywords: py_lazy_vin
Platform: UNKNOWN
Classifier: Development Status :: 2 - Pre-Alpha
Classifier: Intended Audience :: Developers
Classifier: License :: OSI Approved :: MIT License
Classifier: Natural Language :: English
Classifier: Programming Language :: Python :: 2
Classifier: Programming Language :: Python :: 2.7
Classifier: Programming Language :: Python :: 3
Classifier: Programming Language :: Python :: 3.4
Classifier: Programming Language :: Python :: 3.5
Classifier: Programming Language :: Python :: 3.6
Classifier: Programming Language :: Python :: 3.7
Requires-Dist: Click (>=6.0)
